materia/structure/__init__.py
materia/structure/structure.py
materia_structure-1.1.0.dist-info/LICENSE
materia_structure-1.1.0.dist-info/WHEEL
materia_structure-1.1.0.dist-info/METADATA
materia_structure-1.1.0.dist-info/RECORD
